Metadata-Version: 2.1
Name: calculo-horas-ferramentas
Version: 1.0
Summary: Este pacote ira fornecer ferramentas para calculo de horas extras e calculo de horas noturnas
Home-page: UNKNOWN
Author: Paulo Andre Vale Castanha
Author-email: p33castanha@outlook.com
License: UNKNOWN
Keywords: Horas,Extras,Noturnas,Calculo,Adicional
Platform: UNKNOWN
